kihonai/__init__.py
kihonai/example.py
kihonai-0.0.1.dist-info/licenses/LICENSE
kihonai-0.0.1.dist-info/METADATA
kihonai-0.0.1.dist-info/WHEEL
kihonai-0.0.1.dist-info/top_level.txt
kihonai-0.0.1.dist-info/RECORD
