Metadata-Version: 2.4
Name: KihonAi
Version: 0.0.1
Summary: Kihon package
Author-email: Ian Budman <ian@kihon.ai>
License-Expression: MIT
Project-URL: Homepage, https://github.com/pypa/KihonAi
Project-URL: Issues, https://github.com/pypa/KihonAi/issues
Classifier: Programming Language :: Python :: 3
Classifier: Operating System :: OS Independent
Requires-Python: >=3.9
License-File: LICENSE
Dynamic: license-file
